setup.py
pcClustering.egg-info/PKG-INFO
pcClustering.egg-info/SOURCES.txt
pcClustering.egg-info/dependency_links.txt
pcClustering.egg-info/top_level.txt
pcclustering/__init__.py
pcclustering/pcclustering.py