Metadata-Version: 2.1
Name: pcClustering
Version: 0.0.4
Summary: A simple example package for point clustering
Home-page: https://github.com/pypa/sampleproject
Author: Howard Van
Author-email: 2447721464@qq.com
License: UNKNOWN
Platform: UNKNOWN
Classifier: Programming Language :: Python :: 3
Classifier: License :: OSI Approved :: MIT License
Classifier: Operating System :: OS Independent
